ContigNet/VirusCNN_siamese.py
ContigNet/__init__.py
ContigNet/__main__.py
ContigNet/util.py
ContigNet/__pycache__/ContigNet.cpython-39.pyc
ContigNet/__pycache__/VirusCNN_siamese.cpython-310.pyc
ContigNet/__pycache__/VirusCNN_siamese.cpython-39.pyc
ContigNet/__pycache__/__init__.cpython-310.pyc
ContigNet/__pycache__/__init__.cpython-39.pyc
ContigNet/__pycache__/__main__.cpython-310.pyc
ContigNet/__pycache__/__main__.cpython-39.pyc
ContigNet/__pycache__/util.cpython-310.pyc
ContigNet/__pycache__/util.cpython-39.pyc
ContigNet/demo/.ignore/AB027021.fasta
ContigNet/demo/.ignore/AB032553.fasta
ContigNet/demo/.ignore/AB042808.fasta
ContigNet/demo/.ignore/AB050936.fasta
ContigNet/demo/.ignore/GCF_000007925.1_ASM792v1_genomic.fna
ContigNet/demo/host_fasta/GCF_000007845.1_ASM784v1_genomic.fna
ContigNet/demo/virus_fasta/AB024414.fasta
ContigNet/demo/virus_fasta/AB027020.fasta
ContigNet/models/final_model
ContigNet/models/model
ContigNet/models/model.dict
ContigNet-1.0.1.post2.dist-info/LICENSE
ContigNet-1.0.1.post2.dist-info/METADATA
ContigNet-1.0.1.post2.dist-info/WHEEL
ContigNet-1.0.1.post2.dist-info/entry_points.txt
ContigNet-1.0.1.post2.dist-info/top_level.txt
ContigNet-1.0.1.post2.dist-info/RECORD
