Metadata-Version: 2.1
Name: ContigNet
Version: 1.0.1.post2
Summary: ContigNet, a deep learning based phage-host interaction prediction tool
Home-page: https://github.com/tianqitang1/ContigNet
Author: Tianqi Tang
Author-email: tianqit@usc.edu
License: USC-RL v1.0
Platform: any
Classifier: Development Status :: 4 - Beta
Classifier: Intended Audience :: Science/Research
Classifier: License :: Other/Proprietary License
Classifier: Operating System :: OS Independent
Classifier: Programming Language :: Python :: 3 :: Only
Classifier: Programming Language :: Python :: 3.8
Classifier: Programming Language :: Python :: 3.9
Classifier: Programming Language :: Python :: 3.10
Classifier: Programming Language :: Python :: 3.11
Classifier: Topic :: Scientific/Engineering :: Bio-Informatics
Classifier: Topic :: Scientific/Engineering :: Artificial Intelligence
Requires-Python: >=3.8
License-File: LICENSE
Requires-Dist: numpy
Requires-Dist: scipy
Requires-Dist: scikit-learn
Requires-Dist: torch
Requires-Dist: tqdm
Requires-Dist: matplotlib
Requires-Dist: pandas
Requires-Dist: seaborn
Requires-Dist: pyyaml
Requires-Dist: tensorboard
Requires-Dist: h5py
Requires-Dist: ete3
Requires-Dist: biopython
Provides-Extra: test
Requires-Dist: pytest (>=6.0) ; extra == 'test'
Requires-Dist: pytest-cov (>=2.0) ; extra == 'test'
Requires-Dist: mypy (>=0.910) ; extra == 'test'
Requires-Dist: flake8 (>=3.9) ; extra == 'test'
Requires-Dist: tox (>=3.24) ; extra == 'test'
